iOS_tools/crash_helper.py
iOS_tools/custom_exception.py
iOS_tools/device_controll.py
iOS_tools/main.py
iOS_tools-1.0.2.dist-info/METADATA
iOS_tools-1.0.2.dist-info/WHEEL
iOS_tools-1.0.2.dist-info/entry_points.txt
iOS_tools-1.0.2.dist-info/top_level.txt
iOS_tools-1.0.2.dist-info/RECORD
