Metadata-Version: 2.1
Name: iOS-tools
Version: 1.0.2
Summary: iOS tools
Home-page: UNKNOWN
Author: crystal
Author-email: zhuhuiping@shizhuang-inc.com
License: UNKNOWN
Platform: UNKNOWN
Requires-Python: >=3.7
Requires-Dist: py-ios-device
